{
  "folder": "O7chQU1WV48vWR1h",
  "name": "Cursed Reputation",
  "type": "flaw",
  "_id": "JQVKihLvd8G67ZCf",
  "img": "icons/svg/stoned.svg",
  "system": {
    "description": "<p>Sailors are a superstitious lot. Whether the ship really is cursed or not, you have great difficulty recruiting new crewmen to sign on. You get a Penalty Die when rolling to recruit new crew Complement.</p>"
  },
  "effects": [],
  "sort": 0,
  "ownership": {
    "default": 0,
    "gzs91c0iwOtmt0Wp": 3
  },
  "flags": {},
  "_stats": {
    "compendiumSource": null,
    "duplicateSource": null,
    "exportSource": null,
    "coreVersion": "13.351",
    "systemId": "honor-and-intrigue",
    "systemVersion": "0.0.0",
    "createdTime": 1764359629601,
    "modifiedTime": 1764359633174,
    "lastModifiedBy": "gzs91c0iwOtmt0Wp"
  },
  "_key": "!items!JQVKihLvd8G67ZCf"
}
